{
  "ingredients": [
      {
          "name": "Limette",
          "unit": "ST"
      },
      {
          "name": "Ginger Ale",
          "unit": "ST"
      },
      {
          "name": "Orangensaft",
          "unit": "CL"
      },
      {
          "name": "Rohrzucker",
          "unit": "BL"
      },
      {
          "name": "Blue Curacao",
          "unit": "CL"
      },
    {
        "name": "Maracujasaft",
        "unit": "CL"
    },
        {
            "name": "Sahne",
            "unit": "CL"
        },
        {
            "name": "Grenadine",
            "unit": "CL"
        },
        {
            "name": "Limettensaft",
            "unit": "CL"
        },
        {
            "name": "Zitronensaft",
            "unit": "CL"
        }

  ],
  "cocktails": [
        {
            "name": "Luca Spezial",
            "ingredients": [
            {
              "name": "Zitronensaft",
              "amount": 0.5

            },
            {
              "name": "Limettensaft",
              "amount": 1.5

            },
            {
              "name": "Grenadine",
              "amount": 10

            },
                {
                    "name": "Sahne",
                    "amount": 10

                },
                {
                    "name": "Maracujasaft",
                    "amount": 10

                }
          ]
        },
    {
        "name": "Ipanema",
        "ingredients": [
        {
          "name": "Limette",
          "amount": 0.5
          
        },
        {
          "name": "Rohrzucker",
          "amount": 1.5
          
        },
        {
          "name": "Ginger Ale",
          "amount": 10
          
        }
      ]
    },
    {
      "name": "Blue Lagoon",
      "ingredients": [
        {
            "name": "Blue Curacao",
            "amount": 2
        },
        {
          "name": "Orangensaft",
          "amount": 10
        }
      ]
    }
  ]
}
